cc_tk/__init__.py
cc_tk/feature/__init__.py
cc_tk/feature/correlation.py
cc_tk/plot/__init__.py
cc_tk/plot/classification.py
cc_tk/relationship/__init__.py
cc_tk/relationship/distribution.py
cc_tk/relationship/schema.py
cc_tk/relationship/summary.py
cc_tk/relationship/utils.py
cc_tk/relationship/significance/__init__.py
cc_tk/relationship/significance/base.py
cc_tk/relationship/significance/predictiveness.py
cc_tk/relationship/significance/statistical.py
cc_tk/util/__init__.py
cc_tk/util/types.py
clementcome_toolkit-0.6.0.dist-info/METADATA
clementcome_toolkit-0.6.0.dist-info/WHEEL
clementcome_toolkit-0.6.0.dist-info/RECORD
