Metadata-Version: 2.4
Name: clementcome-toolkit
Version: 0.6.0
Summary: My data science toolkit.
Author-email: Clément Côme <clement.come98@gmail.com>
License: MIT
Classifier: Development Status :: 3 - Alpha
Classifier: Intended Audience :: Developers
Classifier: License :: OSI Approved :: MIT License
Classifier: Programming Language :: Python :: 3
Classifier: Programming Language :: Python :: 3.9
Classifier: Programming Language :: Python :: 3.10
Classifier: Programming Language :: Python :: 3.11
Classifier: Programming Language :: Python :: 3.12
Classifier: Programming Language :: Python :: 3.13
Requires-Python: >=3.9
Requires-Dist: matplotlib>=3.8.0
Requires-Dist: numpy>=1.26.1
Requires-Dist: openpyxl>=3.1.2
Requires-Dist: pandas>=2.1.1
Requires-Dist: pandera>=0.18.0
Requires-Dist: pydantic>=2.4.2
Requires-Dist: scikit-learn>=1.3.2
Requires-Dist: scipy>=1.11.3
Requires-Dist: seaborn>=0.13.0
